image_to_table/__init__.py
image_to_table/animation.py
image_to_table/generate.py
image_to_table/json_extractor.py
image_to_table/visualiser.py
Image_to_Table-1.0.3.dist-info/LICENSE
Image_to_Table-1.0.3.dist-info/METADATA
Image_to_Table-1.0.3.dist-info/WHEEL
Image_to_Table-1.0.3.dist-info/top_level.txt
Image_to_Table-1.0.3.dist-info/RECORD
